{
  "name": "good afternoon",
  "description": "",
  "timestamp": "2025-04-15 11:27:23",
  "duration": 1.7715976238250732,
  "frame_count": 98,
  "components": [
    {
      "timestamp": 1.3002204895019531,
      "handshape": "a",
      "orientation": "front",
      "movement": "stationary",
      "confidence": 0.9714734554290771,
      "handedness": "Right"
    },
    {
      "timestamp": 1.3598406314849854,
      "handshape": "a",
      "orientation": "front",
      "movement": "stationary",
      "confidence": 0.9697837233543396,
      "handedness": "Right"
    },
    {
      "timestamp": 1.4228441715240479,
      "handshape": "a",
      "orientation": "front",
      "movement": "stationary",
      "confidence": 0.9710680246353149,
      "handedness": "Right"
    },
    {
      "timestamp": 1.4842736721038818,
      "handshape": "a",
      "orientation": "front",
      "movement": "stationary",
      "confidence": 0.9734237790107727,
      "handedness": "Right"
    },
    {
      "timestamp": 1.546616792678833,
      "handshape": "a",
      "orientation": "front",
      "movement": "stationary",
      "confidence": 0.9708544015884399,
      "handedness": "Right"
    },
    {
      "timestamp": 1.6096765995025635,
      "handshape": "a",
      "orientation": "front",
      "movement": "up",
      "confidence": 0.9696495532989502,
      "handedness": "Right"
    },
    {
      "timestamp": 1.6715877056121826,
      "handshape": "a",
      "orientation": "front",
      "movement": "up",
      "confidence": 0.9692366123199463,
      "handedness": "Right"
    },
    {
      "timestamp": 1.734217643737793,
      "handshape": "a",
      "orientation": "front",
      "movement": "up",
      "confidence": 0.9694353938102722,
      "handedness": "Right"
    },
    {
      "timestamp": 1.8096694946289062,
      "handshape": "a",
      "orientation": "front",
      "movement": "up",
      "confidence": 0.9698807001113892,
      "handedness": "Right"
    },
    {
      "timestamp": 1.8715989589691162,
      "handshape": "a",
      "orientation": "front",
      "movement": "up",
      "confidence": 0.9709275364875793,
      "handedness": "Right"
    },
    {
      "timestamp": 1.9330532550811768,
      "handshape": "a",
      "orientation": "front",
      "movement": "stationary",
      "confidence": 0.9693955183029175,
      "handedness": "Right"
    },
    {
      "timestamp": 1.9971580505371094,
      "handshape": "a",
      "orientation": "front",
      "movement": "stationary",
      "confidence": 0.9687216281890869,
      "handedness": "Right"
    },
    {
      "timestamp": 2.071233034133911,
      "handshape": "a",
      "orientation": "front",
      "movement": "stationary",
      "confidence": 0.9683393836021423,
      "handedness": "Right"
    },
    {
      "timestamp": 2.133211851119995,
      "handshape": "a",
      "orientation": "front",
      "movement": "stationary",
      "confidence": 0.9691476821899414,
      "handedness": "Right"
    },
    {
      "timestamp": 2.1957485675811768,
      "handshape": "a",
      "orientation": "front",
      "movement": "stationary",
      "confidence": 0.9691501259803772,
      "handedness": "Right"
    },
    {
      "timestamp": 2.2538979053497314,
      "handshape": "a",
      "orientation": "front",
      "movement": "down",
      "confidence": 0.9684993624687195,
      "handedness": "Right"
    },
    {
      "timestamp": 2.3181188106536865,
      "handshape": "a",
      "orientation": "front",
      "movement": "down",
      "confidence": 0.9703483581542969,
      "handedness": "Right"
    },
    {
      "timestamp": 2.377931833267212,
      "handshape": "a",
      "orientation": "front",
      "movement": "down",
      "confidence": 0.9692763686180115,
      "handedness": "Right"
    },
    {
      "timestamp": 2.4392457008361816,
      "handshape": "a",
      "orientation": "front",
      "movement": "stationary",
      "confidence": 0.9697272181510925,
      "handedness": "Right"
    },
    {
      "timestamp": 2.5037293434143066,
      "handshape": "a",
      "orientation": "front",
      "movement": "stationary",
      "confidence": 0.9691575169563293,
      "handedness": "Right"
    },
    {
      "timestamp": 2.5655033588409424,
      "handshape": "a",
      "orientation": "front",
      "movement": "stationary",
      "confidence": 0.9686322212219238,
      "handedness": "Right"
    },
    {
      "timestamp": 2.6280791759490967,
      "handshape": "a",
      "orientation": "front",
      "movement": "stationary",
      "confidence": 0.9690977334976196,
      "handedness": "Right"
    },
    {
      "timestamp": 2.689854860305786,
      "handshape": "a",
      "orientation": "front",
      "movement": "stationary",
      "confidence": 0.9698886871337891,
      "handedness": "Right"
    },
    {
      "timestamp": 2.753856897354126,
      "handshape": "a",
      "orientation": "front",
      "movement": "stationary",
      "confidence": 0.9700927138328552,
      "handedness": "Right"
    },
    {
      "timestamp": 2.8145055770874023,
      "handshape": "a",
      "orientation": "front",
      "movement": "stationary",
      "confidence": 0.9703763127326965,
      "handedness": "Right"
    },
    {
      "timestamp": 2.874587059020996,
      "handshape": "a",
      "orientation": "front",
      "movement": "stationary",
      "confidence": 0.9710251092910767,
      "handedness": "Right"
    },
    {
      "timestamp": 2.937446355819702,
      "handshape": "a",
      "orientation": "front",
      "movement": "stationary",
      "confidence": 0.970922589302063,
      "handedness": "Right"
    },
    {
      "timestamp": 2.999627113342285,
      "handshape": "a",
      "orientation": "front",
      "movement": "stationary",
      "confidence": 0.9700682759284973,
      "handedness": "Right"
    },
    {
      "timestamp": 3.0619354248046875,
      "handshape": "a",
      "orientation": "front",
      "movement": "stationary",
      "confidence": 0.9702004194259644,
      "handedness": "Right"
    },
    {
      "timestamp": 3.123858690261841,
      "handshape": "a",
      "orientation": "front",
      "movement": "stationary",
      "confidence": 0.972244143486023,
      "handedness": "Right"
    },
    {
      "timestamp": 3.1838412284851074,
      "handshape": "a",
      "orientation": "front",
      "movement": "stationary",
      "confidence": 0.9709384441375732,
      "handedness": "Right"
    },
    {
      "timestamp": 3.2479982376098633,
      "handshape": "a",
      "orientation": "front",
      "movement": "stationary",
      "confidence": 0.9716669917106628,
      "handedness": "Right"
    },
    {
      "timestamp": 3.3103890419006348,
      "handshape": "a",
      "orientation": "front",
      "movement": "stationary",
      "confidence": 0.9708908796310425,
      "handedness": "Right"
    },
    {
      "timestamp": 3.3718972206115723,
      "handshape": "a",
      "orientation": "front",
      "movement": "stationary",
      "confidence": 0.9705754518508911,
      "handedness": "Right"
    },
    {
      "timestamp": 3.4324703216552734,
      "handshape": "a",
      "orientation": "front",
      "movement": "stationary",
      "confidence": 0.9715232849121094,
      "handedness": "Right"
    },
    {
      "timestamp": 3.4937868118286133,
      "handshape": "a",
      "orientation": "front",
      "movement": "stationary",
      "confidence": 0.9738726615905762,
      "handedness": "Right"
    },
    {
      "timestamp": 3.5551869869232178,
      "handshape": "a",
      "orientation": "front",
      "movement": "stationary",
      "confidence": 0.9720746874809265,
      "handedness": "Right"
    },
    {
      "timestamp": 3.6169185638427734,
      "handshape": "a",
      "orientation": "front",
      "movement": "stationary",
      "confidence": 0.9600818753242493,
      "handedness": "Right"
    },
    {
      "timestamp": 3.679381847381592,
      "handshape": "a",
      "orientation": "front",
      "movement": "right",
      "confidence": 0.8606157898902893,
      "handedness": "Right"
    },
    {
      "timestamp": 3.743134021759033,
      "handshape": "a",
      "orientation": "front",
      "movement": "up",
      "confidence": 0.9,
      "handedness": "Right"
    },
    {
      "timestamp": 3.8037490844726562,
      "handshape": "a",
      "orientation": "front",
      "movement": "up",
      "confidence": 0.9,
      "handedness": "Right"
    },
    {
      "timestamp": 3.86811900138855,
      "handshape": "c",
      "orientation": "front",
      "movement": "right",
      "confidence": 0.9,
      "handedness": "Right"
    },
    {
      "timestamp": 3.941189765930176,
      "handshape": "c",
      "orientation": "front",
      "movement": "right",
      "confidence": 0.9,
      "handedness": "Right"
    },
    {
      "timestamp": 4.003876209259033,
      "handshape": "c",
      "orientation": "front",
      "movement": "right",
      "confidence": 0.9,
      "handedness": "Right"
    },
    {
      "timestamp": 4.063737392425537,
      "handshape": "c",
      "orientation": "front",
      "movement": "right",
      "confidence": 0.9,
      "handedness": "Right"
    },
    {
      "timestamp": 4.125241279602051,
      "handshape": "c",
      "orientation": "front",
      "movement": "right",
      "confidence": 0.9,
      "handedness": "Right"
    },
    {
      "timestamp": 4.186964988708496,
      "handshape": "c",
      "orientation": "front",
      "movement": "right",
      "confidence": 0.9,
      "handedness": "Right"
    },
    {
      "timestamp": 4.25085711479187,
      "handshape": "c",
      "orientation": "front",
      "movement": "right",
      "confidence": 0.9,
      "handedness": "Right"
    },
    {
      "timestamp": 4.310625314712524,
      "handshape": "c",
      "orientation": "front",
      "movement": "right",
      "confidence": 0.9,
      "handedness": "Right"
    },
    {
      "timestamp": 4.372990131378174,
      "handshape": "c",
      "orientation": "front",
      "movement": "right",
      "confidence": 0.9,
      "handedness": "Right"
    },
    {
      "timestamp": 4.433999061584473,
      "handshape": "c",
      "orientation": "front",
      "movement": "right",
      "confidence": 0.9,
      "handedness": "Right"
    },
    {
      "timestamp": 4.496474981307983,
      "handshape": "c",
      "orientation": "front",
      "movement": "right",
      "confidence": 0.9,
      "handedness": "Right"
    },
    {
      "timestamp": 4.557596445083618,
      "handshape": "c",
      "orientation": "front",
      "movement": "stationary",
      "confidence": 0.9,
      "handedness": "Right"
    },
    {
      "timestamp": 4.637359380722046,
      "handshape": "c",
      "orientation": "front",
      "movement": "up",
      "confidence": 0.9,
      "handedness": "Right"
    },
    {
      "timestamp": 4.638363361358643,
      "handshape": "c",
      "orientation": "front",
      "movement": "up",
      "confidence": 0.9,
      "handedness": "Right"
    },
    {
      "timestamp": 4.6929473876953125,
      "handshape": "c",
      "orientation": "front",
      "movement": "up",
      "confidence": 0.9,
      "handedness": "Right"
    },
    {
      "timestamp": 4.759875297546387,
      "handshape": "c",
      "orientation": "front",
      "movement": "stationary",
      "confidence": 0.9,
      "handedness": "Right"
    },
    {
      "timestamp": 4.837347745895386,
      "handshape": "c",
      "orientation": "front",
      "movement": "stationary",
      "confidence": 0.9,
      "handedness": "Right"
    },
    {
      "timestamp": 4.838348627090454,
      "handshape": "c",
      "orientation": "front",
      "movement": "stationary",
      "confidence": 0.9,
      "handedness": "Right"
    },
    {
      "timestamp": 4.892719268798828,
      "handshape": "c",
      "orientation": "front",
      "movement": "stationary",
      "confidence": 0.9,
      "handedness": "Right"
    },
    {
      "timestamp": 4.957261800765991,
      "handshape": "c",
      "orientation": "front",
      "movement": "down",
      "confidence": 0.9,
      "handedness": "Right"
    },
    {
      "timestamp": 5.021363973617554,
      "handshape": "c",
      "orientation": "front",
      "movement": "stationary",
      "confidence": 0.9,
      "handedness": "Right"
    },
    {
      "timestamp": 5.0821921825408936,
      "handshape": "c",
      "orientation": "front",
      "movement": "down",
      "confidence": 0.9,
      "handedness": "Right"
    },
    {
      "timestamp": 5.144752502441406,
      "handshape": "c",
      "orientation": "front",
      "movement": "down",
      "confidence": 0.9,
      "handedness": "Right"
    },
    {
      "timestamp": 5.203100204467773,
      "handshape": "c",
      "orientation": "front",
      "movement": "down",
      "confidence": 0.9,
      "handedness": "Right"
    },
    {
      "timestamp": 5.26737904548645,
      "handshape": "c",
      "orientation": "front",
      "movement": "stationary",
      "confidence": 0.9,
      "handedness": "Right"
    },
    {
      "timestamp": 5.331392526626587,
      "handshape": "c",
      "orientation": "front",
      "movement": "stationary",
      "confidence": 0.9,
      "handedness": "Right"
    },
    {
      "timestamp": 5.390640020370483,
      "handshape": "c",
      "orientation": "front",
      "movement": "stationary",
      "confidence": 0.9,
      "handedness": "Right"
    },
    {
      "timestamp": 5.453731298446655,
      "handshape": "c",
      "orientation": "front",
      "movement": "stationary",
      "confidence": 0.9,
      "handedness": "Right"
    },
    {
      "timestamp": 5.5145323276519775,
      "handshape": "c",
      "orientation": "front",
      "movement": "stationary",
      "confidence": 0.9,
      "handedness": "Right"
    },
    {
      "timestamp": 5.575974225997925,
      "handshape": "c",
      "orientation": "front",
      "movement": "stationary",
      "confidence": 0.9,
      "handedness": "Right"
    },
    {
      "timestamp": 5.636519908905029,
      "handshape": "c",
      "orientation": "front",
      "movement": "stationary",
      "confidence": 0.9,
      "handedness": "Right"
    },
    {
      "timestamp": 5.7166664600372314,
      "handshape": "c",
      "orientation": "front",
      "movement": "up",
      "confidence": 0.9,
      "handedness": "Right"
    },
    {
      "timestamp": 5.717669486999512,
      "handshape": "c",
      "orientation": "front",
      "movement": "up",
      "confidence": 0.9,
      "handedness": "Right"
    },
    {
      "timestamp": 5.758041620254517,
      "handshape": "c",
      "orientation": "front",
      "movement": "up",
      "confidence": 0.9,
      "handedness": "Right"
    },
    {
      "timestamp": 5.824361085891724,
      "handshape": "c",
      "orientation": "front",
      "movement": "stationary",
      "confidence": 0.9,
      "handedness": "Right"
    },
    {
      "timestamp": 5.885592222213745,
      "handshape": "c",
      "orientation": "front",
      "movement": "stationary",
      "confidence": 0.9,
      "handedness": "Right"
    },
    {
      "timestamp": 5.951923608779907,
      "handshape": "c",
      "orientation": "front",
      "movement": "down",
      "confidence": 0.9,
      "handedness": "Right"
    },
    {
      "timestamp": 6.024593353271484,
      "handshape": "c",
      "orientation": "front",
      "movement": "down",
      "confidence": 0.9,
      "handedness": "Right"
    },
    {
      "timestamp": 6.090575695037842,
      "handshape": "c",
      "orientation": "front",
      "movement": "down",
      "confidence": 0.9,
      "handedness": "Right"
    },
    {
      "timestamp": 6.1502296924591064,
      "handshape": "c",
      "orientation": "front",
      "movement": "stationary",
      "confidence": 0.9,
      "handedness": "Right"
    },
    {
      "timestamp": 6.215012550354004,
      "handshape": "c",
      "orientation": "front",
      "movement": "stationary",
      "confidence": 0.9,
      "handedness": "Right"
    },
    {
      "timestamp": 6.275993824005127,
      "handshape": "c",
      "orientation": "front",
      "movement": "stationary",
      "confidence": 0.9,
      "handedness": "Right"
    },
    {
      "timestamp": 6.33582329750061,
      "handshape": "c",
      "orientation": "front",
      "movement": "stationary",
      "confidence": 0.9,
      "handedness": "Right"
    },
    {
      "timestamp": 6.415319442749023,
      "handshape": "c",
      "orientation": "front",
      "movement": "up",
      "confidence": 0.9,
      "handedness": "Right"
    },
    {
      "timestamp": 6.416341066360474,
      "handshape": "c",
      "orientation": "front",
      "movement": "up",
      "confidence": 0.9,
      "handedness": "Right"
    },
    {
      "timestamp": 6.459018707275391,
      "handshape": "c",
      "orientation": "front",
      "movement": "up",
      "confidence": 0.9,
      "handedness": "Right"
    },
    {
      "timestamp": 6.523865461349487,
      "handshape": "c",
      "orientation": "front",
      "movement": "left",
      "confidence": 0.9,
      "handedness": "Right"
    },
    {
      "timestamp": 6.5873212814331055,
      "handshape": "c",
      "orientation": "front",
      "movement": "left",
      "confidence": 0.9,
      "handedness": "Right"
    },
    {
      "timestamp": 6.649528741836548,
      "handshape": "c",
      "orientation": "front",
      "movement": "stationary",
      "confidence": 0.9,
      "handedness": "Right"
    },
    {
      "timestamp": 6.727874279022217,
      "handshape": "c",
      "orientation": "front",
      "movement": "up",
      "confidence": 0.9,
      "handedness": "Right"
    },
    {
      "timestamp": 6.728921175003052,
      "handshape": "c",
      "orientation": "front",
      "movement": "stationary",
      "confidence": 0.9,
      "handedness": "Right"
    },
    {
      "timestamp": 6.784732818603516,
      "handshape": "c",
      "orientation": "front",
      "movement": "left",
      "confidence": 0.9,
      "handedness": "Right"
    },
    {
      "timestamp": 6.849315643310547,
      "handshape": "c",
      "orientation": "front",
      "movement": "down",
      "confidence": 0.9,
      "handedness": "Right"
    },
    {
      "timestamp": 6.911242961883545,
      "handshape": "c",
      "orientation": "front",
      "movement": "down",
      "confidence": 0.9,
      "handedness": "Right"
    },
    {
      "timestamp": 6.990197420120239,
      "handshape": "c",
      "orientation": "front",
      "movement": "down",
      "confidence": 0.9,
      "handedness": "Right"
    },
    {
      "timestamp": 6.991203784942627,
      "handshape": "c",
      "orientation": "front",
      "movement": "down",
      "confidence": 0.9,
      "handedness": "Right"
    },
    {
      "timestamp": 7.046410083770752,
      "handshape": "c",
      "orientation": "front",
      "movement": "down",
      "confidence": 0.9,
      "handedness": "Right"
    }
  ],
  "simplified_sequence": [
    {
      "handshape": "a",
      "orientation": "front",
      "movement": "stationary",
      "handedness": "Right",
      "confidence": 0.9714734554290771,
      "start_time": 0,
      "end_time": 0.30945611000061035,
      "duration": 0.30945611000061035
    },
    {
      "handshape": "a",
      "orientation": "front",
      "movement": "up",
      "handedness": "Right",
      "confidence": 0.9696495532989502,
      "start_time": 0.30945611000061035,
      "end_time": 0.6328327655792236,
      "duration": 0.3233766555786133
    },
    {
      "handshape": "c",
      "orientation": "front",
      "movement": "right",
      "handedness": "Right",
      "confidence": 0.9,
      "start_time": 0.6328327655792236,
      "end_time": 1.322310209274292,
      "duration": 0.6894774436950684
    },
    {
      "handshape": "c",
      "orientation": "front",
      "movement": "stationary",
      "handedness": "Right",
      "confidence": 0.9,
      "start_time": 1.322310209274292,
      "end_time": 1.7715976238250732,
      "duration": 0.44928741455078125
    }
  ]
}